divHretention/__init__.py
divHretention/compute_implantation_coefficients_angle.py
divHretention/compute_inventory.py
divHretention/extract_data.py
divHretention/inventory_T_c.py
divHretention/process_T_c_data.py
divHretention/data/__init__.py
divHretention/data/data_TRIM_energy_angle.csv
divHretention/data/list_of_files.py
divHretention/data/mb_high_temp/T=1.00e+03_c=3.34e+22.csv
divHretention/data/mb_high_temp/T=1.00e+03_c=8.86e+19.csv
divHretention/data/mb_high_temp/T=1.01e+03_c=2.10e+20.csv
divHretention/data/mb_high_temp/T=1.01e+03_c=3.19e+21.csv
divHretention/data/mb_high_temp/T=1.01e+03_c=4.71e+19.csv
divHretention/data/mb_high_temp/T=1.01e+03_c=9.45e+20.csv
divHretention/data/mb_high_temp/T=1.02e+03_c=2.43e+19.csv
divHretention/data/mb_high_temp/T=1.02e+03_c=2.72e+19.csv
divHretention/data/mb_high_temp/T=1.02e+03_c=3.32e+19.csv
divHretention/data/mb_high_temp/T=1.02e+03_c=4.40e+21.csv
divHretention/data/mb_high_temp/T=1.02e+03_c=7.39e+20.csv
divHretention/data/mb_high_temp/T=1.02e+03_c=9.18e+19.csv
divHretention/data/mb_high_temp/T=1.02e+03_c=9.29e+19.csv
divHretention/data/mb_high_temp/T=1.02e+03_c=9.34e+21.csv
divHretention/data/mb_high_temp/T=1.03e+03_c=1.26e+19.csv
divHretention/data/mb_high_temp/T=1.03e+03_c=1.43e+19.csv
divHretention/data/mb_high_temp/T=1.03e+03_c=3.06e+22.csv
divHretention/data/mb_high_temp/T=1.03e+03_c=4.32e+19.csv
divHretention/data/mb_high_temp/T=1.03e+03_c=5.02e+20.csv
divHretention/data/mb_high_temp/T=1.03e+03_c=5.62e+22.csv
divHretention/data/mb_high_temp/T=1.03e+03_c=6.52e+20.csv
divHretention/data/mb_high_temp/T=1.03e+03_c=6.90e+21.csv
divHretention/data/mb_high_temp/T=1.03e+03_c=8.60e+20.csv
divHretention/data/mb_high_temp/T=1.04e+03_c=1.46e+19.csv
divHretention/data/mb_high_temp/T=1.04e+03_c=1.82e+22.csv
divHretention/data/mb_high_temp/T=1.04e+03_c=2.10e+19.csv
divHretention/data/mb_high_temp/T=1.04e+03_c=4.12e+19.csv
divHretention/data/mb_high_temp/T=1.04e+03_c=4.21e+21.csv
divHretention-1.0.dist-info/LICENSE
divHretention-1.0.dist-info/METADATA
divHretention-1.0.dist-info/WHEEL
divHretention-1.0.dist-info/top_level.txt
divHretention-1.0.dist-info/zip-safe
divHretention-1.0.dist-info/RECORD
